tinydb_serialization/__init__.py
tinydb_serialization-2.0.0.dist-info/LICENSE
tinydb_serialization-2.0.0.dist-info/WHEEL
tinydb_serialization-2.0.0.dist-info/METADATA
tinydb_serialization-2.0.0.dist-info/RECORD
