Metadata-Version: 2.1
Name: tinydb-serialization
Version: 2.0.0
Summary: Serialization for objects that TinyDB otherwise couldn't handle
License: MIT
Keywords: database,nosql
Author: Markus Siemens
Author-email: markus@m-siemens.de
Requires-Python: >=3.5,<4.0
Classifier: Development Status :: 5 - Production/Stable
Classifier: Intended Audience :: Developers
Classifier: Intended Audience :: System Administrators
Classifier: License :: OSI Approved :: MIT License
Classifier: Operating System :: OS Independent
Classifier: Programming Language :: Python :: 3
Classifier: Programming Language :: Python :: 3.5
Classifier: Programming Language :: Python :: 3.6
Classifier: Programming Language :: Python :: 3.7
Classifier: Programming Language :: Python :: 3.8
Classifier: Programming Language :: Python :: Implementation :: PyPy
Classifier: Topic :: Database
Classifier: Topic :: Database :: Database Engines/Servers
Classifier: Topic :: Utilities
Requires-Dist: tinydb (>=4.0,<5.0)
